{"/etc/issue.net":"Ubuntu 24.04.4 LTS","antiFeatures":{},"apksigner":"/usr/bin/apksigner","archivePolicy0":[],"commandLine":["/usr/bin/fdroid update"],"disabled":[],"endTimestamp":1779656150692,"failedBuilds":{},"fdroiddata":{"commitId":"893349fe1a0b625e490a6ba8622694b603ca38a5","isDirty":false,"modifiedFiles":[],"untrackedFiles":["config.yml","keystore.p12","repo/YouTube_Music-v9.19.50-patches-v1.29.1-dev.1.apk","repo/categories.txt","repo/entry.jar","repo/entry.json","repo/icons/icon.png","repo/index-v1.jar","repo/index-v1.json","repo/index-v2.json","repo/index.css","repo/index.html","repo/index.jar","repo/index.png","repo/index.xml","repo/placeholder","tmp/apkcache.json","tmp/repo_1779656145000.json"]},"jarsigner":"/usr/lib/jvm/default-java/bin/jarsigner","keytool":"/usr/lib/jvm/default-java/bin/keytool","needsUpdate":[],"noPackages":[],"noUpdateCheck":[],"startTimestamp":1779656142000,"subcommand":"update"}